{"games":[{"awayTeam":{"abbrev":"MTL","score":2},"homeTeam":{"abbrev":"TB","score":1},"gameState":"LIVE","clock":{"timeRemaining":"0:00"},"period":2,"startTimeUTC":"2026-04-21T23:00Z"},{"awayTeam":{"abbrev":"BOS","score":1},"homeTeam":{"abbrev":"BUF","score":0},"gameState":"LIVE","clock":{"timeRemaining":"4:22"},"period":2,"startTimeUTC":"2026-04-21T23:30Z"},{"awayTeam":{"abbrev":"UTA","score":0},"homeTeam":{"abbrev":"VGK","score":0},"gameState":"PRE","clock":{"timeRemaining":"0:00"},"period":0,"startTimeUTC":"2026-04-22T01:30Z"},{"awayTeam":{"abbrev":"LA","score":0},"homeTeam":{"abbrev":"COL","score":0},"gameState":"PRE","clock":{"timeRemaining":"0:00"},"period":0,"startTimeUTC":"2026-04-22T02:00Z"}]}